lazyfpl/__init__.py
lazyfpl/__main__.py
lazyfpl/backevel.py
lazyfpl/cli.py
lazyfpl/conf.py
lazyfpl/constraints.py
lazyfpl/database.py
lazyfpl/differentials.py
lazyfpl/fetch.py
lazyfpl/helpers.py
lazyfpl/ml_model.py
lazyfpl/optimizer.py
lazyfpl/populator.py
lazyfpl/py.typed
lazyfpl/show.py
lazyfpl/structures.py
lazyfpl/team.py
lazyfpl/transfer.py
lazyfpl-0.5.0.dist-info/METADATA
lazyfpl-0.5.0.dist-info/WHEEL
lazyfpl-0.5.0.dist-info/entry_points.txt
lazyfpl-0.5.0.dist-info/licenses/LICENSE
lazyfpl-0.5.0.dist-info/RECORD
