Metadata-Version: 2.3
Name: lazyfpl
Version: 0.5.0
Summary: Fantasy Premier League Team Optimizer - Win at FPL with lazines
Author-email: JeyBee <janbjorge@gmail.com>
License: MIT
Keywords: FPL,data analysis,fantasy premier league,football data,machine learning,python,soccer statistics,sports analytics,team optimization
Classifier: Intended Audience :: Developers
Classifier: Intended Audience :: End Users/Desktop
Classifier: License :: OSI Approved :: MIT License
Classifier: Natural Language :: English
Classifier: Operating System :: MacOS
Classifier: Operating System :: Microsoft :: Windows
Classifier: Operating System :: POSIX :: Linux
Classifier: Programming Language :: Python
Classifier: Programming Language :: Python :: 3.10
Classifier: Programming Language :: Python :: 3.11
Classifier: Programming Language :: Python :: 3.12
Classifier: Programming Language :: Python :: 3.13
Classifier: Topic :: Games/Entertainment
Classifier: Topic :: Scientific/Engineering :: Information Analysis
Classifier: Topic :: Software Development :: Libraries :: Python Modules
Requires-Python: >=3.11
Requires-Dist: more-itertools
Requires-Dist: numpy
Requires-Dist: pydantic
Requires-Dist: pydantic-settings>=2.6.1
Requires-Dist: python-dateutil
Requires-Dist: pytz
Requires-Dist: requests
Requires-Dist: tabulate
Requires-Dist: torch
Requires-Dist: tqdm
Requires-Dist: typer
Provides-Extra: dev
Requires-Dist: mypy; extra == 'dev'
Requires-Dist: pytest; extra == 'dev'
Requires-Dist: ruff; extra == 'dev'
Requires-Dist: tqdm-stubs; extra == 'dev'
Requires-Dist: types-python-dateutil; extra == 'dev'
Requires-Dist: types-pytz; extra == 'dev'
Requires-Dist: types-requests; extra == 'dev'
Requires-Dist: types-tabulate; extra == 'dev'
